LICENSE
MANIFEST.in
README.rst
setup.py
Users/__init__.py
Users/admin.py
Users/apps.py
Users/models.py
Users/tests.py
Users/urls.py
Users/views.py
Users/api/__init__.py
Users/api/serializers.py
Users/api/viewsets.py
Users/api/__pycache__/__init__.cpython-38.pyc
Users/api/__pycache__/serializers.cpython-38.pyc
Users/api/__pycache__/viewsets.cpython-38.pyc
django_samplemed_user_api.egg-info/PKG-INFO
django_samplemed_user_api.egg-info/SOURCES.txt
django_samplemed_user_api.egg-info/dependency_links.txt
django_samplemed_user_api.egg-info/top_level.txt